ngrok_info/__init__.py
ngrok_info-1.2.4.dist-info/LICENSE
ngrok_info-1.2.4.dist-info/METADATA
ngrok_info-1.2.4.dist-info/WHEEL
ngrok_info-1.2.4.dist-info/top_level.txt
ngrok_info-1.2.4.dist-info/RECORD
