Metadata-Version: 2.1
Name: ngrok_info
Version: 1.2.4
Summary: Easy and fast tool written in python 3 to get info about running ngrok tunnel
Home-page: https://github.com/HexagonCore/get-ngrok-tunnel-info
Author: Hexagon Core Development
Author-email: mp3martin.developer@gmail.com
License: MIT
License-File: LICENSE
Requires-Dist: markdown
Requires-Dist: requests
